half_adder.v
module half_adder (A, B, C, Sum);

//inputs
input A;
input B;

//outputs
output C;
output Sum;

//assignments
assign C = A&B;
assign Sum = A^B;

endmodule

full_adder.v
`include "half_adder.v"
module full_adder(A, B, Cin, Cout, Sum);


//inputs
input A;
input B;
input Cin;

//outputs
output Sum;
output Cout;

//wires
wire w0;
wire w1;
wire w2;


//half adders
half_adder U0(.A(A), .B(B), .Sum(w0), .C(w1));
half_adder U1(.A(w0), .B(Cin), .Sum(Sum), .C(w2));

//assignments
assign Cout = w1 ^ w2;

endmodule

full_adder_test.v
`include "full_adder.v"
`timescale 10ns/1ns

module full_adder_test;

    reg A, B, Cin;
    
    wire w0, w1, w2, Sum, Cout;

    full_adder UUT(A, B, Cin, Cout, Sum);

    initial begin
        $display("Start of Test.");
        $dumpfile("full_adder.vcd");
        $dumpvars(0, full_adder_test);
        {A, B, Cin} = 4'd0; #10; $display("%d + %d + %d = %d",A, B, Cin, Cout, Sum);
        {A, B, Cin} = 4'd1; #10; $display("%d + %d + %d = %d",A, B, Cin, Cout, Sum);
        {A, B, Cin} = 4'd2; #10; $display("%d + %d + %d = %d",A, B, Cin, Cout, Sum);
        {A, B, Cin} = 4'd3; #10; $display("%d + %d + %d = %d",A, B, Cin, Cout, Sum);
        {A, B, Cin} = 4'd4; #10; $display("%d + %d + %d = %d",A, B, Cin, Cout, Sum);
        {A, B, Cin} = 4'd5; #10; $display("%d + %d + %d = %d",A, B, Cin, Cout, Sum);
        {A, B, Cin} = 4'd6; #10; $display("%d + %d + %d = %d",A, B, Cin, Cout, Sum);
        {A, B, Cin} = 4'd7; #10; $display("%d + %d + %d = %d",A, B, Cin, Cout, Sum);
        $display("End of Test.");
    end

endmodule

full_adder.vcd
$date
	Mon May 03 23:26:20 2021
$end
$version
	Icarus Verilog
$end
$timescale
	1ns
$end
$scope module full_adder_test $end
$var wire 1 ! Sum $end
$var wire 1 " Cout $end
$var reg 1 # A $end
$var reg 1 $ B $end
$var reg 1 % Cin $end
$scope module UUT $end
$var wire 1 # A $end
$var wire 1 $ B $end
$var wire 1 % Cin $end
$var wire 1 " Cout $end
$var wire 1 & w2 $end
$var wire 1 ' w1 $end
$var wire 1 ( w0 $end
$var wire 1 ! Sum $end
$scope module U0 $end
$var wire 1 # A $end
$var wire 1 $ B $end
$var wire 1 ' C $end
$var wire 1 ( Sum $end
$upscope $end
$scope module U1 $end
$var wire 1 ( A $end
$var wire 1 % B $end
$var wire 1 & C $end
$var wire 1 ! Sum $end
$upscope $end
$upscope $end
$upscope $end
$enddefinitions $end
#0
$dumpvars
0(
0'
0&
0%
0$
0#
0"
0!
$end
#100
1!
1%
#200
1(
1!
1$
0%
#300
1"
1&
0!
1%
#400
0"
0&
1!
1#
0$
0%
#500
1"
1&
0!
1%
#600
1'
0(
0&
0!
1$
0%
#700
1!
1%
