full_adder.v
`include "half_adder.v"
module full_adder(A, B, Cin, Cout, Sum);


//inputs
input A;
input B;
input Cin;

//outputs
output Sum;
output Cout;

//wires
wire w0;
wire w1;
wire w2;


//half adders
half_adder U0(.A(A), .B(B), .Sum(w0), .C(w1));
half_adder U1(.A(w0), .B(Cin), .Sum(Sum), .C(w2));

//assignments
assign Cout = w1 ^ w2;

endmodule

half_adder.v
module half_adder (A, B, C, Sum);

//inputs
input A;
input B;

//outputs
output C;
output Sum;

//assignments
assign C = A&B;
assign Sum = A^B;

endmodule

full.v
`include "half_adder.v"
module top(A, B, Cin, S, Cout);

//inputs
input A;
input B;
input Cin;

//outputs
output S;
output Cout;

//assignments
assign S = A^B^Cin;
assign Cout = ;

endmodule

full_test.v
`include "full_adder.v"
`timescale 10ns/1ns

module full_test;

    reg A, B, Cin;
    
    wire S, Cout;

    top UUT(A, B, Cin, S, Cout);

    initial begin
        $display("Start of Test.");
        $dumpfile("full.vcd");
        $dumpvars(0, full_test);
        {A, B, Cin} = 4'd0; #10; $display("%d + %d + %d = %d", A, B, Cin, S, Cout);
        {A, B, Cin} = 4'd1; #10; $display("%d + %d + %d = %d", A, B, Cin, S, Cout);
        {A, B, Cin} = 4'd2; #10; $display("%d + %d + %d = %d", A, B, Cin, S, Cout);
        {A, B, Cin} = 4'd3; #10; $display("%d + %d + %d = %d", A, B, Cin, S, Cout);
        {A, B, Cin} = 4'd4; #10; $display("%d + %d + %d = %d", A, B, Cin, S, Cout);
        {A, B, Cin} = 4'd5; #10; $display("%d + %d + %d = %d", A, B, Cin, S, Cout);
        {A, B, Cin} = 4'd6; #10; $display("%d + %d + %d = %d", A, B, Cin, S, Cout);
        {A, B, Cin} = 4'd7; #10; $display("%d + %d + %d = %d", A, B, Cin, S, Cout);
        $display("End of Test.");
    end

endmodule

full.vcd
$date
	Mon Feb 15 04:18:54 2021
$end
$version
	Icarus Verilog
$end
$timescale
	1ns
$end
$scope module full_test $end
$var wire 1 ! S $end
$var wire 1 " Cout $end
$var reg 1 # A $end
$var reg 1 $ B $end
$var reg 1 % Cin $end
$scope module UUT $end
$var wire 1 # A $end
$var wire 1 $ B $end
$var wire 1 % Cin $end
$var wire 1 " Cout $end
$var wire 1 ! S $end
$upscope $end
$upscope $end
$enddefinitions $end
#0
$dumpvars
0%
0$
0#
0"
0!
$end
#100
1!
1"
1%
#200
1!
1"
1$
0%
#300
0!
0"
1%
#400
1!
1"
1#
0$
0%
#500
0!
0"
1%
#600
0!
0"
1$
0%
#700
1!
1"
1%
