mux2to1.v
module mux2to1 (A, B, C, Y);

// DATA INPUTS
input A;
input B;

//CONTROL INPUTS
input C;

//OUTPUTS
output Y;

// LOGIC CIRCUIT
assign Y = (A & ~C) | (B & C);

endmodule

mux2to1_8bit.v
`include "mux2to1.v"

module mux2to1_8bit (A, B, C, Y);

// Data inputs
input [7:0] A; 
input [7:0] B;


// Control input
input C;

// Outputs
output [7:0] Y;

//Generator
genvar i;
generate
    for (i = 7; i >= 0; i = i - 1) 
    begin
        mux2to1 U0 (A[i], B[i], C, Y[i]);
    end
endgenerate

endmodule

mux2to1_8bit_test.v
`include "mux2to1_8bit.v"
`timescale 1ns/1ns

module mux2to1_8bit_test;

//DATA INPUTS
reg [7:0] A;
reg [7:0] B;


//CONTROL INPUTS
reg C;

//OUTPUTS
wire [7:0] Y;

//test cases
integer test;
integer total_pass = 2**17;

//UNIT UNDER TEST
mux2to1_8bit UUT (A, B, C, Y);

//logic simulation
initial begin
    $dumpfile ("mux2to1_8bit.vcd");
    $dumpvars (0, mux2to1_8bit_test);

    for (integer test = 0; test < 13172; test++)
    begin
        B = test [7:0];
        A = test [15:8];
        C = test [16];
        #10;

    if (C == 0 && Y != A || C == 1 && Y != B)
        begin
            $display("Test failed.");
            total_pass = total_pass - 1;
        end
    end

    $display("%d tests passed", total_pass);
    $display("Test end.");
end


endmodule

mux2to1_8bit.vcd
$date
	Sun Mar 28 22:38:37 2021
$end
$version
	Icarus Verilog
$end
$timescale
	1ns
$end
$scope module mux2to1_8bit_test $end
$var wire 8 ! Y [7:0] $end
$var reg 8 " A [7:0] $end
$var reg 8 # B [7:0] $end
$var reg 1 $ C $end
$var integer 32 % total_pass [31:0] $end
$scope module UUT $end
$var wire 8 & A [7:0] $end
$var wire 8 ' B [7:0] $end
$var wire 1 $ C $end
$var wire 8 ( Y [7:0] $end
$scope begin genblk1[0] $end
$scope module U0 $end
$var wire 1 ) A $end
$var wire 1 * B $end
$var wire 1 $ C $end
$var wire 1 + Y $end
$upscope $end
$upscope $end
$scope begin genblk1[1] $end
$scope module U0 $end
$var wire 1 , A $end
$var wire 1 - B $end
$var wire 1 $ C $end
$var wire 1 . Y $end
$upscope $end
$upscope $end
$scope begin genblk1[2] $end
$scope module U0 $end
$var wire 1 / A $end
$var wire 1 0 B $end
$var wire 1 $ C $end
$var wire 1 1 Y $end
$upscope $end
$upscope $end
$scope begin genblk1[3] $end
$scope module U0 $end
$var wire 1 2 A $end
$var wire 1 3 B $end
$var wire 1 $ C $end
$var wire 1 4 Y $end
$upscope $end
$upscope $end
$scope begin genblk1[4] $end
$scope module U0 $end
$var wire 1 5 A $end
$var wire 1 6 B $end
$var wire 1 $ C $end
$var wire 1 7 Y $end
$upscope $end
$upscope $end
$scope begin genblk1[5] $end
$scope module U0 $end
$var wire 1 8 A $end
$var wire 1 9 B $end
$var wire 1 $ C $end
$var wire 1 : Y $end
$upscope $end
$upscope $end
$scope begin genblk1[6] $end
$scope module U0 $end
$var wire 1 ; A $end
$var wire 1 < B $end
$var wire 1 $ C $end
$var wire 1 = Y $end
$upscope $end
$upscope $end
$scope begin genblk1[7] $end
$scope module U0 $end
$var wire 1 > A $end
$var wire 1 ? B $end
$var wire 1 $ C $end
$var wire 1 @ Y $end
$upscope $end
$upscope $end
$upscope $end
$scope begin $ivl_for_loop0 $end
$var integer 32 A test [31:0] $end
$upscope $end
$upscope $end
$enddefinitions $end
#0
$dumpvars
b0 A
0@
0?
0>
0=
0<
0;
0:
09
08
07
06
05
04
03
02
01
00
0/
0.
0-
0,
0+
0*
0)
b0 (
b0 '
b0 &
b100000000000000000 %
0$
b0 #
b0 "
b0 !
$end
#10
1*
b1 #
b1 '
b1 A
#20
1-
0*
b10 #
b10 '
b10 A
#30
1*
b11 #
b11 '
b11 A
#40
10
0-
0*
b100 #
b100 '
b100 A
#50
1*
b101 #
b101 '
b101 A
#60
1-
0*
b110 #
b110 '
b110 A
#70
1*
b111 #
b111 '
b111 A
#80
13
00
0-
0*
b1000 #
b1000 '
b1000 A
#90
1*
b1001 #
b1001 '
b1001 A
#100
1-
0*
b1010 #
b1010 '
b1010 A
#110
1*
b1011 #
b1011 '
b1011 A
#120
10
0-
0*
b1100 #
b1100 '
b1100 A
#130
1*
b1101 #
b1101 '
b1101 A
#140
1-
0*
b1110 #
b1110 '
b1110 A
#150
1*
b1111 #
b1111 '
b1111 A
#160
16
03
00
0-
0*
b10000 #
b10000 '
b10000 A
#170
1*
b10001 #
b10001 '
b10001 A
#180
1-
0*
b10010 #
b10010 '
b10010 A
#190
1*
b10011 #
b10011 '
b10011 A
#200
10
0-
0*
b10100 #
b10100 '
b10100 A
#210
1*
b10101 #
b10101 '
b10101 A
#220
1-
0*
b10110 #
b10110 '
b10110 A
#230
1*
b10111 #
b10111 '
b10111 A
#240
13
00
0-
0*
b11000 #
b11000 '
b11000 A
#250
1*
b11001 #
b11001 '
b11001 A
#260
1-
0*
b11010 #
b11010 '
b11010 A
#270
1*
b11011 #
b11011 '
b11011 A
#280
10
0-
0*
b11100 #
b11100 '
b11100 A
#290
1*
b11101 #
b11101 '
b11101 A
#300
1-
0*
b11110 #
b11110 '
b11110 A
#310
1*
b11111 #
b11111 '
b11111 A
#320
19
06
03
00
0-
0*
b100000 #
b100000 '
b100000 A
#330
1*
b100001 #
b100001 '
b100001 A
#340
1-
0*
b100010 #
b100010 '
b100010 A
#350
1*
b100011 #
b100011 '
b100011 A
#360
10
0-
0*
b100100 #
b100100 '
b100100 A
#370
1*
b100101 #
b100101 '
b100101 A
#380
1-
0*
b100110 #
b100110 '
b100110 A
#390
1*
b100111 #
b100111 '
b100111 A
#400
13
00
0-
0*
b101000 #
b101000 '
b101000 A
#410
1*
b101001 #
b101001 '
b101001 A
#420
1-
0*
b101010 #
b101010 '
b101010 A
#430
1*
b101011 #
b101011 '
b101011 A
#440
10
0-
0*
b101100 #
b101100 '
b101100 A
#450
1*
b101101 #
b101101 '
b101101 A
#460
1-
0*
b101110 #
b101110 '
b101110 A
#470
1*
b101111 #
b101111 '
b101111 A
#480
16
03
00
0-
0*
b110000 #
b110000 '
b110000 A
#490
1*
b110001 #
b110001 '
b110001 A
#500
1-
0*
b110010 #
b110010 '
b110010 A
#510
1*
b110011 #
b110011 '
b110011 A
#520
10
0-
0*
b110100 #
b110100 '
b110100 A
#530
1*
b110101 #
b110101 '
b110101 A
#540
1-
0*
b110110 #
b110110 '
b110110 A
#550
1*
b110111 #
b110111 '
b110111 A
#560
13
00
0-
0*
b111000 #
b111000 '
b111000 A
#570
1*
b111001 #
b111001 '
b111001 A
#580
1-
0*
b111010 #
b111010 '
b111010 A
#590
1*
b111011 #
b111011 '
b111011 A
#600
10
0-
0*
b111100 #
b111100 '
b111100 A
#610
1*
b111101 #
b111101 '
b111101 A
#620
1-
0*
b111110 #
b111110 '
b111110 A
#630
1*
b111111 #
b111111 '
b111111 A
#640
1<
09
06
03
00
0-
0*
b1000000 #
b1000000 '
b1000000 A
#650
1*
b1000001 #
b1000001 '
b1000001 A
#660
1-
0*
b1000010 #
b1000010 '
b1000010 A
#670
1*
b1000011 #
b1000011 '
b1000011 A
#680
10
0-
0*
b1000100 #
b1000100 '
b1000100 A
#690
1*
b1000101 #
b1000101 '
b1000101 A
#700
1-
0*
b1000110 #
b1000110 '
b1000110 A
#710
1*
b1000111 #
b1000111 '
b1000111 A
#720
13
00
0-
0*
b1001000 #
b1001000 '
b1001000 A
#730
1*
b1001001 #
b1001001 '
b1001001 A
#740
1-
0*
b1001010 #
b1001010 '
b1001010 A
#750
1*
b1001011 #
b1001011 '
b1001011 A
#760
10
0-
0*
b1001100 #
b1001100 '
b1001100 A
#770
1*
b1001101 #
b1001101 '
b1001101 A
#780
1-
0*
b1001110 #
b1001110 '
b1001110 A
#790
1*
b1001111 #
b1001111 '
b1001111 A
#800
16
03
00
0-
0*
b1010000 #
b1010000 '
b1010000 A
#810
1*
b1010001 #
b1010001 '
b1010001 A
#820
1-
0*
b1010010 #
b1010010 '
b1010010 A
#830
1*
b1010011 #
b1010011 '
b1010011 A
#840
10
0-
0*
b1010100 #
b1010100 '
b1010100 A
#850
1*
b1010101 #
b1010101 '
b1010101 A
#860
1-
0*
b1010110 #
b1010110 '
b1010110 A
#870
1*
b1010111 #
b1010111 '
b1010111 A
#880
13
00
0-
0*
b1011000 #
b1011000 '
b1011000 A
#890
1*
b1011001 #
b1011001 '
b1011001 A
#900
1-
0*
b1011010 #
b1011010 '
b1011010 A
#910
1*
b1011011 #
b1011011 '
b1011011 A
#920
10
0-
0*
b1011100 #
b1011100 '
b1011100 A
#930
1*
b1011101 #
b1011101 '
b1011101 A
#940
1-
0*
b1011110 #
b1011110 '
b1011110 A
#950
1*
b1011111 #
b1011111 '
b1011111 A
#960
19
06
03
00
0-
0*
b1100000 #
b1100000 '
b1100000 A
#970
1*
b1100001 #
b1100001 '
b1100001 A
#980
1-
0*
b1100010 #
b1100010 '
b1100010 A
#990
1*
b1100011 #
b1100011 '
b1100011 A
#1000
10
0-
0*
b1100100 #
b1100100 '
b1100100 A
#1010
1*
b1100101 #
b1100101 '
b1100101 A
#1020
1-
0*
b1100110 #
b1100110 '
b1100110 A
#1030
1*
b1100111 #
b1100111 '
b1100111 A
#1040
13
00
0-
0*
b1101000 #
b1101000 '
b1101000 A
#1050
1*
b1101001 #
b1101001 '
b1101001 A
#1060
1-
0*
b1101010 #
b1101010 '
b1101010 A
#1070
1*
b1101011 #
b1101011 '
b1101011 A
#1080
10
0-
0*
b1101100 #
b1101100 '
b1101100 A
#1090
1*
b1101101 #
b1101101 '
b1101101 A
#1100
1-
0*
b1101110 #
b1101110 '
b1101110 A
#1110
1*
b1101111 #
b1101111 '
b1101111 A
#1120
16
03
00
0-
0*
b1110000 #
b1110000 '
b1110000 A
#1130
1*
b1110001 #
b1110001 '
b1110001 A
#1140
1-
0*
b1110010 #
b1110010 '
b1110010 A
#1150
1*
b1110011 #
b1110011 '
b1110011 A
#1160
10
0-
0*
b1110100 #
b1110100 '
b1110100 A
#1170
1*
b1110101 #
b1110101 '
b1110101 A
#1180
1-
0*
b1110110 #
b1110110 '
b1110110 A
#1190
1*
b1110111 #
b1110111 '
b1110111 A
#1200
13
00
0-
0*
b1111000 #
b1111000 '
b1111000 A
#1210
1*
b1111001 #
b1111001 '
b1111001 A
#1220
1-
0*
b1111010 #
b1111010 '
b1111010 A
#1230
1*
b1111011 #
b1111011 '
b1111011 A
#1240
10
0-
0*
b1111100 #
b1111100 '
b1111100 A
#1250
1*
b1111101 #
b1111101 '
b1111101 A
#1260
1-
0*
b1111110 #
b1111110 '
b1111110 A
#1270
1*
b1111111 #
b1111111 '
b1111111 A
#1280
1?
0<
09
06
03
00
0-
0*
b10000000 #
b10000000 '
b10000000 A
#1290
1*
b10000001 #
b10000001 '
b10000001 A
#1300
1-
0*
b10000010 #
b10000010 '
b10000010 A
#1310
1*
b10000011 #
b10000011 '
b10000011 A
#1320
10
0-
0*
b10000100 #
b10000100 '
b10000100 A
#1330
1*
b10000101 #
b10000101 '
b10000101 A
#1340
1-
0*
b10000110 #
b10000110 '
b10000110 A
#1350
1*
b10000111 #
b10000111 '
b10000111 A
#1360
13
00
0-
0*
b10001000 #
b10001000 '
b10001000 A
#1370
1*
b10001001 #
b10001001 '
b10001001 A
#1380
1-
0*
b10001010 #
b10001010 '
b10001010 A
#1390
1*
b10001011 #
b10001011 '
b10001011 A
#1400
10
0-
0*
b10001100 #
b10001100 '
b10001100 A
#1410
1*
b10001101 #
b10001101 '
b10001101 A
#1420
1-
0*
b10001110 #
b10001110 '
b10001110 A
#1430
1*
b10001111 #
b10001111 '
b10001111 A
#1440
16
03
00
0-
0*
b10010000 #
b10010000 '
b10010000 A
#1450
1*
b10010001 #
b10010001 '
b10010001 A
#1460
1-
0*
b10010010 #
b10010010 '
b10010010 A
#1470
1*
b10010011 #
b10010011 '
b10010011 A
#1480
10
0-
0*
b10010100 #
b10010100 '
b10010100 A
#1490
1*
b10010101 #
b10010101 '
b10010101 A
#1500
1-
0*
b10010110 #
b10010110 '
b10010110 A
#1510
1*
b10010111 #
b10010111 '
b10010111 A
#1520
13
00
0-
0*
b10011000 #
b10011000 '
b10011000 A
#1530
1*
b10011001 #
b10011001 '
b10011001 A
#1540
1-
0*
b10011010 #
b10011010 '
b10011010 A
#1550
1*
b10011011 #
b10011011 '
b10011011 A
#1560
10
0-
0*
b10011100 #
b10011100 '
b10011100 A
#1570
1*
b10011101 #
b10011101 '
b10011101 A
#1580
1-
0*
b10011110 #
b10011110 '
b10011110 A
#1590
1*
b10011111 #
b10011111 '
b10011111 A
#1600
19
06
03
00
0-
0*
b10100000 #
b10100000 '
b10100000 A
#1610
1*
b10100001 #
b10100001 '
b10100001 A
#1620
1-
0*
b10100010 #
b10100010 '
b10100010 A
#1630
1*
b10100011 #
b10100011 '
b10100011 A
#1640
10
0-
0*
b10100100 #
b10100100 '
b10100100 A
#1650
1*
b10100101 #
b10100101 '
b10100101 A
#1660
1-
0*
b10100110 #
b10100110 '
b10100110 A
#1670
1*
b10100111 #
b10100111 '
b10100111 A
#1680
13
00
0-
0*
b10101000 #
b10101000 '
b10101000 A
#1690
1*
b10101001 #
b10101001 '
b10101001 A
#1700
1-
0*
b10101010 #
b10101010 '
b10101010 A
#1710
1*
b10101011 #
b10101011 '
b10101011 A
#1720
10
0-
0*
b10101100 #
b10101100 '
b10101100 A
#1730
1*
b10101101 #
b10101101 '
b10101101 A
#1740
1-
0*
b10101110 #
b10101110 '
b10101110 A
#1750
1*
b10101111 #
b10101111 '
b10101111 A
#1760
16
03
00
0-
0*
b10110000 #
b10110000 '
b10110000 A
#1770
1*
b10110001 #
b10110001 '
b10110001 A
#1780
1-
0*
b10110010 #
b10110010 '
b10110010 A
#1790
1*
b10110011 #
b10110011 '
b10110011 A
#1800
10
0-
0*
b10110100 #
b10110100 '
b10110100 A
#1810
1*
b10110101 #
b10110101 '
b10110101 A
#1820
1-
0*
b10110110 #
b10110110 '
b10110110 A
#1830
1*
b10110111 #
b10110111 '
b10110111 A
#1840
13
00
0-
0*
b10111000 #
b10111000 '
b10111000 A
#1850
1*
b10111001 #
b10111001 '
b10111001 A
#1860
1-
0*
b10111010 #
b10111010 '
b10111010 A
#1870
1*
b10111011 #
b10111011 '
b10111011 A
#1880
10
0-
0*
b10111100 #
b10111100 '
b10111100 A
#1890
1*
b10111101 #
b10111101 '
b10111101 A
#1900
1-
0*
b10111110 #
b10111110 '
b10111110 A
#1910
1*
b10111111 #
b10111111 '
b10111111 A
#1920
1<
09
06
03
00
0-
0*
b11000000 #
b11000000 '
b11000000 A
#1930
1*
b11000001 #
b11000001 '
b11000001 A
#1940
1-
0*
b11000010 #
b11000010 '
b11000010 A
#1950
1*
b11000011 #
b11000011 '
b11000011 A
#1960
10
0-
0*
b11000100 #
b11000100 '
b11000100 A
#1970
1*
b11000101 #
b11000101 '
b11000101 A
#1980
1-
0*
b11000110 #
b11000110 '
b11000110 A
#1990
1*
b11000111 #
b11000111 '
b11000111 A
#2000
13
00
0-
0*
b11001000 #
b11001000 '
b11001000 A
#2010
1*
b11001001 #
b11001001 '
b11001001 A
#2020
1-
0*
b11001010 #
b11001010 '
b11001010 A
#2030
1*
b11001011 #
b11001011 '
b11001011 A
#2040
10
0-
0*
b11001100 #
b11001100 '
b11001100 A
#2050
1*
b11001101 #
b11001101 '
b11001101 A
#2060
1-
0*
b11001110 #
b11001110 '
b11001110 A
#2070
1*
b11001111 #
b11001111 '
b11001111 A
#2080
16
03
00
0-
0*
b11010000 #
b11010000 '
b11010000 A
#2090
1*
b11010001 #
b11010001 '
b11010001 A
#2100
1-
0*
b11010010 #
b11010010 '
b11010010 A
#2110
1*
b11010011 #
b11010011 '
b11010011 A
#2120
10
0-
0*
b11010100 #
b11010100 '
b11010100 A
#2130
1*
b11010101 #
b11010101 '
b11010101 A
#2140
1-
0*
b11010110 #
b11010110 '
b11010110 A
#2150
1*
b11010111 #
b11010111 '
b11010111 A
#2160
13
00
0-
0*
b11011000 #
b11011000 '
b11011000 A
#2170
1*
b11011001 #
b11011001 '
b11011001 A
#2180
1-
0*
b11011010 #
b11011010 '
b11011010 A
#2190
1*
b11011011 #
b11011011 '
b11011011 A
#2200
10
0-
0*
b11011100 #
b11011100 '
b11011100 A
#2210
1*
b11011101 #
b11011101 '
b11011101 A
#2220
1-
0*
b11011110 #
b11011110 '
b11011110 A
#2230
1*
b11011111 #
b11011111 '
b11011111 A
#2240
19
06
03
00
0-
0*
b11100000 #
b11100000 '
b11100000 A
#2250
1*
b11100001 #
b11100001 '
b11100001 A
#2260
1-
0*
b11100010 #
b11100010 '
b11100010 A
#2270
1*
b11100011 #
b11100011 '
b11100011 A
#2280
10
0-
0*
b11100100 #
b11100100 '
b11100100 A
#2290
1*
b11100101 #
b11100101 '
b11100101 A
#2300
1-
0*
b11100110 #
b11100110 '
b11100110 A
#2310
1*
b11100111 #
b11100111 '
b11100111 A
#2320
13
00
0-
0*
b11101000 #
b11101000 '
b11101000 A
#2330
1*
b11101001 #
b11101001 '
b11101001 A
#2340
1-
0*
b11101010 #
b11101010 '
b11101010 A
#2350
1*
b11101011 #
b11101011 '
b11101011 A
#2360
10
0-
0*
b11101100 #
b11101100 '
b11101100 A
#2370
1*
b11101101 #
b11101101 '
b11101101 A
#2380
1-
0*
b11101110 #
b11101110 '
b11101110 A
#2390
1*
b11101111 #
b11101111 '
b11101111 A
#2400
16
03
00
0-
0*
b11110000 #
b11110000 '
b11110000 A
#2410
1*
b11110001 #
b11110001 '
b11110001 A
#2420
1-
0*
b11110010 #
b11110010 '
b11110010 A
#2430
1*
b11110011 #
b11110011 '
b11110011 A
#2440
10
0-
0*
b11110100 #
b11110100 '
b11110100 A
#2450
1*
b11110101 #
b11110101 '
b11110101 A
#2460
1-
0*
b11110110 #
b11110110 '
b11110110 A
#2470
1*
b11110111 #
b11110111 '
b11110111 A
#2480
13
00
0-
0*
b11111000 #
b11111000 '
b11111000 A
#2490
1*
b11111001 #
b11111001 '
b11111001 A
#2500
1-
0*
b11111010 #
b11111010 '
b11111010 A
#2510
1*
b11111011 #
b11111011 '
b11111011 A
#2520
10
0-
0*
b11111100 #
b11111100 '
b11111100 A
#2530
1*
b11111101 #
b11111101 '
b11111101 A
#2540
1-
0*
b11111110 #
b11111110 '
b11111110 A
#2550
1*
b11111111 #
b11111111 '
b11111111 A
#2560
b1 !
b1 (
1+
1)
0?
0<
09
06
03
00
0-
0*
b1 "
b1 &
b0 #
b0 '
b100000000 A
#2570
1*
b1 #
b1 '
b100000001 A
#2580
1-
0*
b10 #
b10 '
b100000010 A
#2590
1*
b11 #
b11 '
b100000011 A
#2600
10
0-
0*
b100 #
b100 '
b100000100 A
#2610
1*
b101 #
b101 '
b100000101 A
#2620
1-
0*
b110 #
b110 '
b100000110 A
#2630
1*
b111 #
b111 '
b100000111 A
#2640
13
00
0-
0*
b1000 #
b1000 '
b100001000 A
#2650
1*
b1001 #
b1001 '
b100001001 A
#2660
1-
0*
b1010 #
b1010 '
b100001010 A
#2670
1*
b1011 #
b1011 '
b100001011 A
#2680
10
0-
0*
b1100 #
b1100 '
b100001100 A
#2690
1*
b1101 #
b1101 '
b100001101 A
#2700
1-
0*
b1110 #
b1110 '
b100001110 A
#2710
1*
b1111 #
b1111 '
b100001111 A
#2720
16
03
00
0-
0*
b10000 #
b10000 '
b100010000 A
#2730
1*
b10001 #
b10001 '
b100010001 A
#2740
1-
0*
b10010 #
b10010 '
b100010010 A
#2750
1*
b10011 #
b10011 '
b100010011 A
#2760
10
0-
0*
b10100 #
b10100 '
b100010100 A
#2770
1*
b10101 #
b10101 '
b100010101 A
#2780
1-
0*
b10110 #
b10110 '
b100010110 A
#2790
1*
b10111 #
b10111 '
b100010111 A
#2800
13
00
0-
0*
b11000 #
b11000 '
b100011000 A
#2810
1*
b11001 #
b11001 '
b100011001 A
#2820
1-
0*
b11010 #
b11010 '
b100011010 A
#2830
1*
b11011 #
b11011 '
b100011011 A
#2840
10
0-
0*
b11100 #
b11100 '
b100011100 A
#2850
1*
b11101 #
b11101 '
b100011101 A
#2860
1-
0*
b11110 #
b11110 '
b100011110 A
#2870
1*
b11111 #
b11111 '
b100011111 A
#2880
19
06
03
00
0-
0*
b100000 #
b100000 '
b100100000 A
#2890
1*
b100001 #
b100001 '
b100100001 A
#2900
1-
0*
b100010 #
b100010 '
b100100010 A
#2910
1*
b100011 #
b100011 '
b100100011 A
#2920
10
0-
0*
b100100 #
b100100 '
b100100100 A
#2930
1*
b100101 #
b100101 '
b100100101 A
#2940
1-
0*
b100110 #
b100110 '
b100100110 A
#2950
1*
b100111 #
b100111 '
b100100111 A
#2960
13
00
0-
0*
b101000 #
b101000 '
b100101000 A
#2970
1*
b101001 #
b101001 '
b100101001 A
#2980
1-
0*
b101010 #
b101010 '
b100101010 A
#2990
1*
b101011 #
b101011 '
b100101011 A
#3000
10
0-
0*
b101100 #
b101100 '
b100101100 A
#3010
1*
b101101 #
b101101 '
b100101101 A
#3020
1-
0*
b101110 #
b101110 '
b100101110 A
#3030
1*
b101111 #
b101111 '
b100101111 A
#3040
16
03
00
0-
0*
b110000 #
b110000 '
b100110000 A
#3050
1*
b110001 #
b110001 '
b100110001 A
#3060
1-
0*
b110010 #
b110010 '
b100110010 A
#3070
1*
b110011 #
b110011 '
b100110011 A
#3080
10
0-
0*
b110100 #
b110100 '
b100110100 A
#3090
1*
b110101 #
b110101 '
b100110101 A
#3100
1-
0*
b110110 #
b110110 '
b100110110 A
#3110
1*
b110111 #
b110111 '
b100110111 A
#3120
13
00
0-
0*
b111000 #
b111000 '
b100111000 A
#3130
1*
b111001 #
b111001 '
b100111001 A
#3140
1-
0*
b111010 #
b111010 '
b100111010 A
#3150
1*
b111011 #
b111011 '
b100111011 A
#3160
10
0-
0*
b111100 #
b111100 '
b100111100 A
#3170
1*
b111101 #
b111101 '
b100111101 A
#3180
1-
0*
b111110 #
b111110 '
b100111110 A
#3190
1*
b111111 #
b111111 '
b100111111 A
#3200
1<
09
06
03
00
0-
0*
b1000000 #
b1000000 '
b101000000 A
#3210
1*
b1000001 #
b1000001 '
b101000001 A
#3220
1-
0*
b1000010 #
b1000010 '
b101000010 A
#3230
1*
b1000011 #
b1000011 '
b101000011 A
#3240
10
0-
0*
b1000100 #
b1000100 '
b101000100 A
#3250
1*
b1000101 #
b1000101 '
b101000101 A
#3260
1-
0*
b1000110 #
b1000110 '
b101000110 A
#3270
1*
b1000111 #
b1000111 '
b101000111 A
#3280
13
00
0-
0*
b1001000 #
b1001000 '
b101001000 A
#3290
1*
b1001001 #
b1001001 '
b101001001 A
#3300
1-
0*
b1001010 #
b1001010 '
b101001010 A
#3310
1*
b1001011 #
b1001011 '
b101001011 A
#3320
10
0-
0*
b1001100 #
b1001100 '
b101001100 A
#3330
1*
b1001101 #
b1001101 '
b101001101 A
#3340
1-
0*
b1001110 #
b1001110 '
b101001110 A
#3350
1*
b1001111 #
b1001111 '
b101001111 A
#3360
16
03
00
0-
0*
b1010000 #
b1010000 '
b101010000 A
#3370
1*
b1010001 #
b1010001 '
b101010001 A
#3380
1-
0*
b1010010 #
b1010010 '
b101010010 A
#3390
1*
b1010011 #
b1010011 '
b101010011 A
#3400
10
0-
0*
b1010100 #
b1010100 '
b101010100 A
#3410
1*
b1010101 #
b1010101 '
b101010101 A
#3420
1-
0*
b1010110 #
b1010110 '
b101010110 A
#3430
1*
b1010111 #
b1010111 '
b101010111 A
#3440
13
00
0-
0*
b1011000 #
b1011000 '
b101011000 A
#3450
1*
b1011001 #
b1011001 '
b101011001 A
#3460
1-
0*
b1011010 #
b1011010 '
b101011010 A
#3470
1*
b1011011 #
b1011011 '
b101011011 A
#3480
10
0-
0*
b1011100 #
b1011100 '
b101011100 A
#3490
1*
b1011101 #
b1011101 '
b101011101 A
#3500
1-
0*
b1011110 #
b1011110 '
b101011110 A
#3510
1*
b1011111 #
b1011111 '
b101011111 A
#3520
19
06
03
00
0-
0*
b1100000 #
b1100000 '
b101100000 A
#3530
1*
b1100001 #
b1100001 '
b101100001 A
#3540
1-
0*
b1100010 #
b1100010 '
b101100010 A
#3550
1*
b1100011 #
b1100011 '
b101100011 A
#3560
10
0-
0*
b1100100 #
b1100100 '
b101100100 A
#3570
1*
b1100101 #
b1100101 '
b101100101 A
#3580
1-
0*
b1100110 #
b1100110 '
b101100110 A
#3590
1*
b1100111 #
b1100111 '
b101100111 A
#3600
13
00
0-
0*
b1101000 #
b1101000 '
b101101000 A
#3610
1*
b1101001 #
b1101001 '
b101101001 A
#3620
1-
0*
b1101010 #
b1101010 '
b101101010 A
#3630
1*
b1101011 #
b1101011 '
b101101011 A
#3640
10
0-
0*
b1101100 #
b1101100 '
b101101100 A
#3650
1*
b1101101 #
b1101101 '
b101101101 A
#3660
1-
0*
b1101110 #
b1101110 '
b101101110 A
#3670
1*
b1101111 #
b1101111 '
b101101111 A
#3680
16
03
00
0-
0*
b1110000 #
b1110000 '
b101110000 A
#3690
1*
b1110001 #
b1110001 '
b101110001 A
#3700
1-
0*
b1110010 #
b1110010 '
b101110010 A
#3710
1*
b1110011 #
b1110011 '
b101110011 A
#3720
10
0-
0*
b1110100 #
b1110100 '
b101110100 A
#3730
1*
b1110101 #
b1110101 '
b101110101 A
#3740
1-
0*
b1110110 #
b1110110 '
b101110110 A
#3750
1*
b1110111 #
b1110111 '
b101110111 A
#3760
13
00
0-
0*
b1111000 #
b1111000 '
b101111000 A
#3770
1*
b1111001 #
b1111001 '
b101111001 A
#3780
1-
0*
b1111010 #
b1111010 '
b101111010 A
#3790
1*
b1111011 #
b1111011 '
b101111011 A
#3800
10
0-
0*
b1111100 #
b1111100 '
b101111100 A
#3810
1*
b1111101 #
b1111101 '
b101111101 A
#3820
1-
0*
b1111110 #
b1111110 '
b101111110 A
#3830
1*
b1111111 #
b1111111 '
b101111111 A
#3840
1?
0<
09
06
03
00
0-
0*
b10000000 #
b10000000 '
b110000000 A
#3850
1*
b10000001 #
b10000001 '
b110000001 A
#3860
1-
0*
b10000010 #
b10000010 '
b110000010 A
#3870
1*
b10000011 #
b10000011 '
b110000011 A
#3880
10
0-
0*
b10000100 #
b10000100 '
b110000100 A
#3890
1*
b10000101 #
b10000101 '
b110000101 A
#3900
1-
0*
b10000110 #
b10000110 '
b110000110 A
#3910
1*
b10000111 #
b10000111 '
b110000111 A
#3920
13
00
0-
0*
b10001000 #
b10001000 '
b110001000 A
#3930
1*
b10001001 #
b10001001 '
b110001001 A
#3940
1-
0*
b10001010 #
b10001010 '
b110001010 A
#3950
1*
b10001011 #
b10001011 '
b110001011 A
#3960
10
0-
0*
b10001100 #
b10001100 '
b110001100 A
#3970
1*
b10001101 #
b10001101 '
b110001101 A
#3980
1-
0*
b10001110 #
b10001110 '
b110001110 A
#3990
1*
b10001111 #
b10001111 '
b110001111 A
#4000
16
03
00
0-
0*
b10010000 #
b10010000 '
b110010000 A
#4010
1*
b10010001 #
b10010001 '
b110010001 A
#4020
1-
0*
b10010010 #
b10010010 '
b110010010 A
#4030
1*
b10010011 #
b10010011 '
b110010011 A
#4040
10
0-
0*
b10010100 #
b10010100 '
b110010100 A
#4050
1*
b10010101 #
b10010101 '
b110010101 A
#4060
1-
0*
b10010110 #
b10010110 '
b110010110 A
#4070
1*
b10010111 #
b10010111 '
b110010111 A
#4080
13
00
0-
0*
b10011000 #
b10011000 '
b110011000 A
#4090
1*
b10011001 #
b10011001 '
b110011001 A
#4100
1-
0*
b10011010 #
b10011010 '
b110011010 A
#4110
1*
b10011011 #
b10011011 '
b110011011 A
#4120
10
0-
0*
b10011100 #
b10011100 '
b110011100 A
#4130
1*
b10011101 #
b10011101 '
b110011101 A
#4140
1-
0*
b10011110 #
b10011110 '
b110011110 A
#4150
1*
b10011111 #
b10011111 '
b110011111 A
#4160
19
06
03
00
0-
0*
b10100000 #
b10100000 '
b110100000 A
#4170
1*
b10100001 #
b10100001 '
b110100001 A
#4180
1-
0*
b10100010 #
b10100010 '
b110100010 A
#4190
1*
b10100011 #
b10100011 '
b110100011 A
#4200
10
0-
0*
b10100100 #
b10100100 '
b110100100 A
#4210
1*
b10100101 #
b10100101 '
b110100101 A
#4220
1-
0*
b10100110 #
b10100110 '
b110100110 A
#4230
1*
b10100111 #
b10100111 '
b110100111 A
#4240
13
00
0-
0*
b10101000 #
b10101000 '
b110101000 A
#4250
1*
b10101001 #
b10101001 '
b110101001 A
#4260
1-
0*
b10101010 #
b10101010 '
b110101010 A
#4270
1*
b10101011 #
b10101011 '
b110101011 A
#4280
10
0-
0*
b10101100 #
b10101100 '
b110101100 A
#4290
1*
b10101101 #
b10101101 '
b110101101 A
#4300
1-
0*
b10101110 #
b10101110 '
b110101110 A
#4310
1*
b10101111 #
b10101111 '
b110101111 A
#4320
16
03
00
0-
0*
b10110000 #
b10110000 '
b110110000 A
#4330
1*
b10110001 #
b10110001 '
b110110001 A
#4340
1-
0*
b10110010 #
b10110010 '
b110110010 A
#4350
1*
b10110011 #
b10110011 '
b110110011 A
#4360
10
0-
0*
b10110100 #
b10110100 '
b110110100 A
#4370
1*
b10110101 #
b10110101 '
b110110101 A
#4380
1-
0*
b10110110 #
b10110110 '
b110110110 A
#4390
1*
b10110111 #
b10110111 '
b110110111 A
#4400
13
00
0-
0*
b10111000 #
b10111000 '
b110111000 A
#4410
1*
b10111001 #
b10111001 '
b110111001 A
#4420
1-
0*
b10111010 #
b10111010 '
b110111010 A
#4430
1*
b10111011 #
b10111011 '
b110111011 A
#4440
10
0-
0*
b10111100 #
b10111100 '
b110111100 A
#4450
1*
b10111101 #
b10111101 '
b110111101 A
