mux2to1.v
module mux2to1 (A, B, C, Y);

// DATA INPUTS
input A;
input B;

//CONTROL INPUTS
input C;

//OUTPUTS
output Y;

// LOGIC CIRCUIT
assign Y = (A & ~C) | (B & C);

endmodule

mux2to1_tb.v
`timescale 1ns/1ns
`include "mux2to1.v"

module mux2to1_tb;

//inputs
reg A;
reg B;

// control input
reg C;

//output
wire Y;

// unit under test
mux2to1 UUT (A, B, C, Y);

// logic simulation
initial begin
    $dumpfile("mux2to1.vcd");
    $dumpvars(0, mux2to1_tb);

    for(integer i = 0; i < 8; i=i+1) begin
        {A, B, C} = i;#10

        if (Y != ((A&~C | (B & C)))) begin
            $display("Test case FAILED for minterm %d", i);
        end
        else begin
            $display("test case passed for minterm %d", i);
        end

    end
    $finish;
end

endmodule

mux2to1.vcd
$date
	Thu Nov 12 15:57:47 2020
$end
$version
	Icarus Verilog
$end
$timescale
	1ns
$end
$scope module mux2to1_tb $end
$var wire 1 ! Y $end
$var reg 1 " A $end
$var reg 1 # B $end
$var reg 1 $ C $end
$scope module UUT $end
$var wire 1 " A $end
$var wire 1 # B $end
$var wire 1 $ C $end
$var wire 1 ! Y $end
$upscope $end
$scope begin $ivl_for_loop0 $end
$var integer 32 % i [31:0] $end
$upscope $end
$upscope $end
$enddefinitions $end
#0
$dumpvars
b0 %
0$
0#
0"
0!
$end
#10
1$
b1 %
#20
1#
0$
b10 %
#30
1!
1$
b11 %
#40
1"
0#
0$
b100 %
#50
0!
1$
b101 %
#60
1!
1#
0$
b110 %
#70
1$
b111 %
#80
b1000 %
